{"options":{"validator":{"$jsonSchema":{"properties":{"round":{"bsonType":"string"},"player1":{"bsonType":"string","description":"Tag of player1 (on smash.gg)"},"player2":{"bsonType":"string","description":"Tag of player2 (on smash.gg)"},"games":{"bsonType":"array","items":{"bsonType":"object","required":["gamenum","player1","player2","stage","winner","filepath"],"properties":{"gamenum":{"bsonType":"int","minimum":{"$numberInt":"1"},"maximum":{"$numberInt":"5"}},"player1":{"bsonType":"object","description":"Data for the SET winner, not game winner","required":["character","color","inputsPerSecond","openingsPerKill","damagePerOpening","neutralWinRatio","counterHitRatio","tag"],"properties":{"openingsPerKill":{"bsonType":["number","null"]},"damagePerOpening":{"bsonType":["number","null"]},"neutralWinRatio":{"bsonType":["number","null"]},"counterHitRatio":{"bsonType":["number","null"]},"tag":{"bsonType":"string"},"character":{"bsonType":"string"},"color":{"bsonType":"string"},"inputsPerSecond":{"bsonType":["number","null"]}}},"player2":{"bsonType":"object","description":"Data for the SET lower, not game loser","required":["character","color","inputsPerSecond","openingsPerKill","damagePerOpening","neutralWinRatio","counterHitRatio","tag"],"properties":{"openingsPerKill":{"bsonType":["number","null"]},"damagePerOpening":{"bsonType":["number","null"]},"neutralWinRatio":{"bsonType":["number","null"]},"counterHitRatio":{"bsonType":["number","null"]},"tag":{"bsonType":"string"},"character":{"bsonType":"string"},"color":{"bsonType":"string"},"inputsPerSecond":{"bsonType":["number","null"]}}},"stage":{"bsonType":"string"},"winner":{"description":"Must be 'player1' or 'player2'","bsonType":["string","null"]},"filepath":{"bsonType":"string"}}}},"tournament":{"bsonType":"string"}},"bsonType":"object","required":["tournament","round","player1","player2","games"]}}},"indexes":[{"v":{"$numberInt":"2"},"key":{"_id":{"$numberInt":"1"}},"name":"_id_","ns":"smashdb.sets"},{"v":{"$numberInt":"2"},"unique":true,"key":{"tournament":{"$numberInt":"1"},"round":{"$numberInt":"1"},"player1":{"$numberInt":"1"},"player2":{"$numberInt":"1"}},"name":"tournament_1_round_1_player1_1_player2_1","ns":"smashdb.sets"}],"uuid":"ced27feeab5e487c9dc972a332e361f4"}